LICENSE
MANIFEST.in
README.md
requirements.txt
setup.py
Lupr/__init__.py
Lupr/main.py
Lupr.egg-info/PKG-INFO
Lupr.egg-info/SOURCES.txt
Lupr.egg-info/dependency_links.txt
Lupr.egg-info/entry_points.txt
Lupr.egg-info/requires.txt
Lupr.egg-info/top_level.txt
Lupr/controllers/__init__.py
Lupr/controllers/controller.py
Lupr/model/__init__.py
Lupr/model/model.py
Lupr/resources/__init__.py
Lupr/resources/images.py
Lupr/resources/images.qrc
Lupr/resources/img/lup.svg
Lupr/views/__init__.py
Lupr/views/interval_prompt.ui
Lupr/views/interval_prompt_ui.py
Lupr/views/interval_prompt_view.py
Lupr/views/main_view.py
Lupr/worker/__init__.py
Lupr/worker/record_worker.py