Metadata-Version: 2.1
Name: Lupr
Version: 1.5.42
Summary: Lup recorder
Home-page: https://gitlab.com/azzamsa/lupr
Author: azzamsa
Author-email: azzam@azzamsa.com
License: GPLv3
Platform: UNKNOWN
Classifier: License :: OSI Approved :: MIT License
Classifier: Programming Language :: Python :: 3
Classifier: Programming Language :: Python :: 3.6
Classifier: Programming Language :: Python :: Implementation :: CPython
